augmenta_ru/BackTranslationAugmenter.py
augmenta_ru/ContextualAugmenter.py
augmenta_ru/EDA.py
augmenta_ru/SynonymReplacer.py
augmenta_ru/TextAugmenter.py
augmenta_ru/__init__.py
augmenta_ru/RuLeanALBERT/__init__.py
augmenta_ru/RuLeanALBERT/arguments.py
augmenta_ru/RuLeanALBERT/data.py
augmenta_ru/RuLeanALBERT/field_collator.py
augmenta_ru/RuLeanALBERT/finetune_mlm.py
augmenta_ru/RuLeanALBERT/models.py
augmenta_ru/RuLeanALBERT/predict_on_lidirus.py
augmenta_ru/RuLeanALBERT/run_aux_peer.py
augmenta_ru/RuLeanALBERT/run_trainer.py
augmenta_ru/RuLeanALBERT/src/__init__.py
augmenta_ru/RuLeanALBERT/src/huggingface_auth.py
augmenta_ru/RuLeanALBERT/src/utils.py
augmenta_ru/RuLeanALBERT/src/models/__init__.py
augmenta_ru/RuLeanALBERT/src/models/albert.py
augmenta_ru/RuLeanALBERT/src/models/config.py
augmenta_ru/RuLeanALBERT/src/models/lean_albert.py
augmenta_ru/RuLeanALBERT/src/models/transformer.py
augmenta_ru/RuLeanALBERT/src/modules/__init__.py
augmenta_ru/RuLeanALBERT/src/modules/attn.py
augmenta_ru/RuLeanALBERT/src/modules/ffn.py
augmenta_ru/RuLeanALBERT/src/modules/functional.py
augmenta_ru/RuLeanALBERT/src/modules/linear.py
augmenta_ru/RuLeanALBERT/src/modules/pixelfly.py
augmenta_ru/RuLeanALBERT/src/modules/rotary.py
augmenta_ru/RuLeanALBERT/src/modules/sequence.py
augmenta_ru/RuLeanALBERT/src/training/__init__.py
augmenta_ru/RuLeanALBERT/src/training/callback.py
augmenta_ru/RuLeanALBERT/src/training/hf_trainer.py
augmenta_ru/RuLeanALBERT/src/training/lamb_8bit.py
augmenta_ru/RuLeanALBERT/src/training/sync.py
augmenta_ru/RuLeanALBERT/tasks/__init__.py
augmenta_ru/RuLeanALBERT/tasks/base.py
augmenta_ru/RuLeanALBERT/tasks/mlm/__init__.py
augmenta_ru/RuLeanALBERT/tasks/mlm/data.py
augmenta_ru/RuLeanALBERT/tasks/mlm/task.py
augmenta_ru/RuLeanALBERT/tasks/mlm/whole_word_mask.py
augmenta_ru-0.1.4.dist-info/METADATA
augmenta_ru-0.1.4.dist-info/WHEEL
augmenta_ru-0.1.4.dist-info/top_level.txt
augmenta_ru-0.1.4.dist-info/RECORD
