Metadata-Version: 2.4
Name: augmenta-ru
Version: 0.1.4
Summary: Text augmentation methods for Russian NLP
Author-email: Protasov Aleksandr <mmerihsehc@icloud.com>
License-Expression: MIT
Project-URL: Homepage, https://github.com/tymillnyc/augmenta-ru
Keywords: nlp,text augmentation,russian
Classifier: Programming Language :: Python :: 3
Classifier: Operating System :: OS Independent
Requires-Dist: deep-translator
Requires-Dist: transformers>=4.40.0
Requires-Dist: numpy<2.0,>=1.21
Requires-Dist: torch
Requires-Dist: requests
Requires-Dist: gensim
Requires-Dist: pymorphy3
Requires-Dist: pymystem3
Requires-Dist: natasha
Requires-Dist: nltk
Requires-Dist: sentencepiece
